QATLibrary/QATLibrary.py
QATLibrary/TLSAdapter.py
QATLibrary/__init__.py
QATLibrary/__main__.py
QATLibrary/cli.py
QATLibrary/version.py
QATLibrary/templates/TestCases.csv
QATLibrary/templates/config.yaml
QATLibrary-23.5.3.dist-info/LICENSE.md
QATLibrary-23.5.3.dist-info/METADATA
QATLibrary-23.5.3.dist-info/WHEEL
QATLibrary-23.5.3.dist-info/entry_points.txt
QATLibrary-23.5.3.dist-info/top_level.txt
QATLibrary-23.5.3.dist-info/RECORD
