Metadata-Version: 2.1
Name: QATLibrary
Version: 23.5.3
Summary: Data/Configuration Driven REST API Test Automation Library. Can be used as a Robot Framework Library or as standalone CLI tool.
Home-page: https://github.com/toil-free/QATLibrary.git
Author: Sharif Rahman
Author-email: shrif.sbu@gmail.com
License: MIT
Project-URL: Docs, https://github.com/toil-free/QATLibrary/README.md
Project-URL: Issue Tracker, https://github.com/toil-free/QATLibrary/issues
Platform: UNKNOWN
Classifier: Development Status :: 5 - Production/Stable
Classifier: Intended Audience :: Developers
Classifier: License :: OSI Approved :: MIT License
Classifier: Operating System :: OS Independent
Classifier: Programming Language :: Python
Classifier: Programming Language :: Python :: 3.6
Classifier: Programming Language :: Python :: 3.7
Classifier: Programming Language :: Python :: 3.8
Classifier: Programming Language :: Python :: 3.9
Classifier: Programming Language :: Python :: 3.10
Classifier: Programming Language :: Python :: 3.11
Classifier: Programming Language :: Python :: Implementation :: CPython
Classifier: Programming Language :: Python :: Implementation :: PyPy
License-File: LICENSE.md
Requires-Dist: requests (>2)
Requires-Dist: robotframework (>4)
Requires-Dist: requests-oauthlib (>1)
Requires-Dist: pyyaml (>5)
Requires-Dist: jsonschema (>3)
Requires-Dist: termcolor (>1.0)
